	<mxDefaultToolbar as="toolbar">
		<add as="connect" mode="connect" icon="images/connect.gif"><![CDATA[
			function (editor)
			{
			
				if (editor.defaultEdge != null) {
					editor.defaultEdge.style = null;
				}
			}
		]]>
		</add>
		<add as="connect" mode="connect" icon="images/straight.gif"><![CDATA[
			function (editor)
			{

				if (editor.defaultEdge != null)
				{
					editor.defaultEdge.style = 'straightConnector';
				}
			}
		]]></add>
		<add as="connect" mode="connect" icon="images/arrow.gif"><![CDATA[
			function (editor)
			{
				if (editor.defaultEdge != null)
				{
					editor.defaultEdge.style = 'arrowConnector';
				}
			}
		]]></add>
		<br/><br/>
		<!--
		<add as="Text" template="text" icon="images/text.gif"/>
		<add as="Container" template="container" icon="images/swimlane.gif"/>
		<add as="Rectangle" template="rectangle" icon="images/rectangle.gif"/>
		<add as="Rounded" template="rounded" icon="images/rounded.gif"/>
		
		
		<add as="Rhombus" template="shape" style="rhombus" icon="images/rhombus.gif"/>
		<add as="Triangle" template="actor" style="triangle" icon="images/triangle.gif"/>
		<add as="Hexagon" template="cloud" style="hexagon" icon="images/hexagon.gif"/>
		<add as="Actor" template="actor" style="actor" icon="images/actor.gif"/>
		<add as="Cylinder" template="shape" style="cylinder" icon="images/cylinder.gif"/>
		<add as="Cloud" template="cloud" style="cloud" icon="images/cloud.gif"/>
		<add as="Line" template="hline" style="hline" icon="images/hline.gif"/>
		<add as="Image" template="image" icon="images/image.gif"/>
	-->
		teste
		<add as="Unidade de Apresentação" template="presentationUnit" icon="images/rounded.gif"/>
		<add as="Unidade de Apresentação" template="alwaysAccessiblePresentationUnit" icon="images/rounded.gif"/>
		<add as="Ponto de Abertura" template="openingPoint" icon="images/ellipse.gif"/>
		<add as="Ponto de Encerramento" template="closurePoint" icon="images/doubleellipse.gif"/>
		<add as="Indicador de Progresso" template="progressIndicator" icon="images/rectangle.gif"/>
		<add as="Ação do Usuário" template="userAction" icon="images/rectangle.gif"/>
		<add as="Conteúdo de Alerta" template="notificationAlertOrConfirmation" icon="images/rectangle.gif"/>
		<add as="Conteúdo de Alerta" template="requiredUserAction" icon="images/rectangle.gif"/>
		<add as="Processo do Sistema" template="systemProcess" icon="images/rectangle.gif"/>
		<add as="Coleção de Dados" template="dataCollection" icon="images/rectangle.gif"/>


	</mxDefaultToolbar>